README.md
setup.py
dwm/__init__.py
dwm/cleaning.py
dwm/dwm.py
dwm/dwmmain.py
dwm/helpers.py
dwm/wrappers.py
dwm.egg-info/PKG-INFO
dwm.egg-info/SOURCES.txt
dwm.egg-info/dependency_links.txt
dwm.egg-info/requires.txt
dwm.egg-info/top_level.txt
dwm/test/__init__.py
dwm/test/test_apply_udfs.py
dwm/test/test_configs.py
dwm/test/test_copy_value.py
dwm/test/test_deriveIncludes.py
dwm/test/test_deriveRegex.py
dwm/test/test_deriveValue.py
dwm/test/test_derive_includes.py
dwm/test/test_derive_regex.py
dwm/test/test_derive_value.py
dwm/test/test_dwm.py
dwm/test/test_dwm_init.py
dwm/test/test_fieldSpecificLookup.py
dwm/test/test_fieldSpecificRegex.py
dwm/test/test_genericLookup.py
dwm/test/test_genericRegex.py
dwm/test/test_normIncludes.py
dwm/test/test_normLookup.py
dwm/test/test_normRegex.py
dwm/test/test_norm_include.py
dwm/test/test_norm_lookup.py
dwm/test/test_norm_regex.py
dwm/test/test_records.py
dwm/test/test_udf.py
dwm/test/test_val_fs_lookup.py
dwm/test/test_val_fs_regex.py
dwm/test/test_val_g_lookup.py
dwm/test/test_val_g_regex.py