Metadata-Version: 1.1
Name: dwm
Version: 1.1.0
Summary: Best practices for marketing data quality management
Home-page: https://github.com/rh-marketingops/dwm
Author: Jeremiah Coleman
Author-email: colemanja91@gmail.com
License: GNU General Public License
Keywords: marketing automation data quality cleanse washing cleaning
Platform: any
Classifier: Programming Language :: Python
Classifier: Development Status :: 4 - Beta
Classifier: Natural Language :: English
Classifier: Environment :: Web Environment
Classifier: Intended Audience :: Developers
Classifier: License :: OSI Approved :: Apache Software License
Classifier: Operating System :: OS Independent
Classifier: Topic :: Software Development :: Libraries :: Python Modules
Classifier: Topic :: Software Development :: Libraries :: Application Frameworks
